CHANGES.md
LICENSE.md
MANIFEST.in
README.md
dare.conf
distribute_setup.py
setup.py
DARE.egg-info/PKG-INFO
DARE.egg-info/SOURCES.txt
DARE.egg-info/dependency_links.txt
DARE.egg-info/entry_points.txt
DARE.egg-info/requires.txt
DARE.egg-info/top_level.txt
bin/__init__.py
bin/dare_run.py
dare/__init__.py
dare/states.py
dare/core/__init__.py
dare/core/dare_manager.py
dare/daredb/__init__.py
dare/daredb/bfast_1.cu
dare/daredb/echo_hello.cu
dare/daredb/pilot.cfg
dare/helpers/__init__.py
dare/helpers/cfgparser.py
dare/helpers/misc.py
dare/helpers/prepareworkflow.py
dare/helpers/stepunit.py
dare/helpers/updater.py
examples/localhost.dare
examples/localhost_two_steps.dare
examples/lonestar.dare
examples/lonestar_not_data_tranfer.dare
examples/qb.dare
examples/ranger.dare
examples/complicated_examples/complicated_example.dare