Metadata-Version: 1.0
Name: DARE
Version: 0.8.0175
Summary: Dynamic Application Runtime Environment
Home-page: https://github.com/saga-project/DARE
Author: Sharath Maddineni
Author-email: smaddineni@cct.lsu.edu
License: MIT
Platform: UNKNOWN
